{
  "id": "01010016",
  "title": "风云会",
  "title_normalized": "风云会",
  "alt_titles": [
    "龙虎斗"
  ],
  "source_collection": "戏考",
  "source_id": "01000000",
  "source_note": "根据《戏考》第十册整理",
  "pages": 4,
  "characters": [
    {
      "name": "赵匡胤",
      "role_type": "红生",
      "gender": "unknown"
    },
    {
      "name": "呼延赞",
      "role_type": "净",
      "gender": "male"
    }
  ],
  "plot_summary": "宋太祖赵匡胤，被困河东。欧阳方专权，擅杀功臣呼延寿廷。时呼延寿廷家属在乐家寨，闻报，其子呼延赞，\n年未弱冠，而臂力过人。闻信，急欲报仇，遂率师犯河东。宋军当之，无不披靡。赵匡胤得报大惊，不得\n已亲自临阵会战。不数合，被呼延赞击至大败。旋见呼延赞似在马上瞌睡，赵匡胤举鞭欲击，忽现黑虎形，\n遂止。既而呼延赞欲击赵匡胤，亦见有金龙出现，鞭不能下。呼延赞知赵匡胤确是真主，乃即离鞍投地，拜\n降赵匡胤于马下，立誓扶保大宋，铲除诸寇云。",
  "notes": "此剧与《下河东》相接。",
  "full_text": "风云会 宋太祖赵匡胤，被困河东。欧阳方专权，擅杀功臣呼延寿廷。时呼延寿廷家属在乐家寨，闻报，其子呼延赞，\n年未弱冠，而臂力过人。闻信，急欲报仇，遂率师犯河东。宋军当之，无不披靡。赵匡胤得报大惊，不得\n已亲自临阵会战。不数合，被呼延赞击至大败。旋见呼延赞似在马上瞌睡，赵匡胤举鞭欲击，忽现黑虎形，\n遂止。既而呼延赞欲击赵匡胤，亦见有金龙出现，鞭不能下。呼延赞知赵匡胤确是真主，乃即离鞍投地，拜\n降赵匡胤于马下，立誓扶保大宋，铲除诸寇云。 【第一场】\n（八龙套引赵匡胤同上，四太监同上。）\n赵匡胤 （引子） 龙争虎斗，这干戈，何日里罢休？\n（念） 蛟龙无水困沙滩，似却明珠土内埋。奸贼诓孤河东地，不知何日转回还。\n（白） 孤，乾德王赵。可恨欧阳藩将孤诓至河东，七载有余。困得孤内无粮草，外无\n救兵。命黄兴前去打探，未见回报。\n（黄兴上。）\n黄兴 （念） 打探军情事，奏与万岁知。\n（白） 臣黄兴见驾，吾王万岁！\n赵匡胤 （白） 打探哪路军情，一一奏来。\n黄兴 （白） 臣探得罗家山发来一哨人马，昨日鞭坠白龙，今日叫骂御营，特来奏与万岁得\n知。\n赵匡胤 （白） 再探！\n黄兴 （白） 领旨。\n（黄兴下。）\n赵匡胤 （白） 且住，黄兴奏道：罗家山发来一哨人马，昨日鞭坠白龙，今日叫骂御营。此誓\n叫孤难解也！\n（唢呐二黄慢板）探马儿不住得飞来报：\n他报道罗家山兵发一哨。\n杏黄旗不住得空中飘摇，\n吓坏了满营中大小英豪。\n恨河东刘冲贼打来战表，\n他要夺孤王的锦绣龙朝。\n欧阳藩在金殿帅印挂了，\n呼寿廷倒作了马前先行。\n困河东有七载须发白了，\n但不知何日里才的回朝？\n在头上摘下了飞龙帽，\n在身上脱下了滚龙袍。\n（白） 孤的玲珑吓！\n（唢呐二黄慢板）玲珑铠甲丝条绕，\n杀人妙计有千条。\nhttp://scripts.xikao.com/play/01010016 2018-08-23\n中国京剧戏考 《风云会》 2\n御林军与孤巡营哨，\n（八龙套同下。）\n赵匡胤 （唢呐二黄慢板）把守御营要勤劳。\n叫槽头将孤的龙驹马鞍韂备好，\n（赵匡胤下。马童上，备马。）\n马童 （白） 请爷上马。\n（赵匡胤上。）\n赵匡胤 （唢呐二黄慢板）这是孤无能将亲把兵交。\n（赵匡胤、马童同下。）\n【第二场】\n（〖急急风〗。呼延赞、八龙套同上。）\n呼延赞 （笑） 哈哈哈，吓，哈哈哈！\n（呼延赞、八龙套同下。）\n【第三场】\n（赵匡胤上。）\n赵匡胤 （二黄摇板） 催马来在战场道，\n会一会罗家山那家英豪。\n呼延赞 （内二黄导板） 乌骓马不住得吮声吼，\n（呼延赞上。）\n呼延赞 （二黄慢板） 打将鞭一举鬼神愁！\n催马儿来至在御营口，\n（白） 呀呔！\n（二黄慢板） 叫一声乾德王快出营头！\n赵匡胤 （二黄慢板） 只见他乌油盔乌油甲，\n皂罗袍上绣团花。\n跨下了一骑乌骓马，\n打将钢鞭手内拿。\n问一声小将名和姓，\n通上名来好动杀法！\n呼延赞 （二黄慢板） 家住在河南汴梁城，\n我的父名叫呼寿廷。\n若问小将名和姓，\n呼延赞，\n（二黄摇板） 就是少爷的名！\n赵匡胤 （二黄摇板） 孤道呼家无有后，\n原来还有后代根。\n不通名姓走了罢，\n呼延赞 （二黄摇板） 钢鞭不打无名人！\n赵匡胤 （二黄摇板） 乾德王现在黄罗帐，\n我是他驾前一小军。\n呼延赞 （二黄摇板） 看你不像军家样，\n定是御营乾德王！\n赵匡胤 （二黄摇板） 少有关西闯帝邦，\n岂肯过伏小儿郎？\n若问孤王名和姓，\n孤就是御营乾德王！\n（赵匡胤、呼延赞同开打，赵匡胤下，呼延赞追下。赵匡胤上。）\n赵匡胤 （二黄摇板） 催马来在战场下，\n小将到来顺说他。\nhttp://scripts.xikao.com/play/01010016 2018-08-23\n中国京剧戏考 《风云会》 3\n（呼延赞上。）\n呼延赞 （二黄摇板） 我父身犯何条律，\n为何一命问斩刑？\n赵匡胤 （二黄导板） 小将军暂息雷霆怒，\n（二黄慢板） 细听孤王说分明：\n恨河东刘冲贼战表打定，\n他要夺孤王的锦绣龙廷。\n欧阳藩在金殿挂了帅印，\n你的父倒作了马前先行。\n三更时那胡儿前来偷营，\n满营中俱言道反了寿廷。\n一个斩字未曾出口，\n欧阳藩拔宝剑杀尔的父亲！\n呼延赞 （二黄摇板） 君不传旨谁敢斩？\n哪一个大胆乱杀人！\n赵匡胤 （二黄摇板） 兵权落在奸贼手，\n孤王也要听令行。\n呼延赞 （二黄摇板） 不会为君死了罢，\n苍天再降紫微星！\n赵匡胤 （二黄摇板） 小将保孤回朝转，\n孤封你前殿王？\n呼延赞 （白） 不要！\n赵匡胤 （二黄摇板） 后殿王？\n呼延赞 （白） 不要！\n赵匡胤 （二黄摇板） 一十八驾总兵王？\n呼延赞 （白） 呸！\n（二黄摇板） 万里江山我不要，\n一心要报杀父仇！\n赵匡胤 （二黄摇板） 小将不必逞刚强，\n呼延赞 （二黄摇板） 罗家山前自为王！\n赵匡胤 （二黄摇板） 孤王与你分上下！\n（赵匡胤、呼延赞同开打，赵匡胤下，呼延赞追下。）\n【第四场】\n（龙形、虎形同上。赵匡胤上，呼延赞追上。）\n赵匡胤 （二黄导板） 人困马乏难交战，\n（白） 吓！\n（二黄摇板） 只见小将睡雕鞍。\n手使金锏朝下打，\n只见黑虎奔了山！\n呼延赞 （二黄导板） 梦儿里梦见了我父到，\n（白） 吓！\n（二黄摇板） 只见昏王睡鞍鞒。\n手使钢鞭朝下打，\n只见赤火龙一条！\n扳鞍离镫下战马，\n三呼万岁饶恕咱！\n赵匡胤 （西皮导板） 耳边厢又听得三呼万岁，\n（西皮慢板） 想必是我朝中发来救兵。\n猛然间睁开了丹凤眼，\n呼延赞 （白） 万岁！\n赵匡胤 （西皮慢板） 又只见，\nhttp://scripts.xikao.com/play/01010016 2018-08-23\n中国京剧戏考 《风云会》 4\n（西皮快板） 小将跌跪在马前。\n在马上擒孤擒不住，\n诓孤下马难上难！\n呼延赞 （西皮快板） 万岁不必心害怕，\n呼延赞保你坐中华！\n赵匡胤 （西皮快板） 你若保孤坐中华，\n可对苍天把誓发？\n呼延赞 （西皮快板） 万岁命我把誓发，\n尊一声苍天听根芽：\n呼延赞保主若有假，\n死在千军万马踏！\n赵匡胤 （西皮快板） 一见小将把誓发，\n不由孤王喜笑发。\n左思右想不下马，\n金锏挑起小卿家。\n呼延赞 （西皮快板） 走上前来参王驾，\n赵匡胤 （西皮快板） 孤王传旨且平身。\n呼延赞 （西皮快板） 杀父仇人哪一个？\n赵匡胤 （西皮快板） 欧阳藩是尔对头人！\n呼延赞 （西皮快板） 问声奸贼今何在？\n赵匡胤 （白） 随孤来，\n（西皮快板） 不在前营在后营。\n呼延赞 （西皮快板） 辞王别驾跨战马，\n后营去把奸贼杀！\n（三笑） 哈哈哈，吓，哈哈哈！\n赵匡胤 （西皮快板） 喜呵呵来笑呵呵，\n孤王收了黑阎罗。\n今日收了这员将，\n哪怕胡儿动干戈！\n（赵匡胤、呼延赞同下。）\n（完）\nhttp://scripts.xikao.com/play/01010016 2018-08-23\nPowered by TCPDF (www.tcpdf.org)",
  "topics": [
    {
      "topic_id": 11,
      "weight": 0.5697
    },
    {
      "topic_id": 7,
      "weight": 0.2985
    },
    {
      "topic_id": 21,
      "weight": 0.1221
    }
  ],
  "drama_type": "家庭伦理",
  "statistics": {
    "scene_count": 4,
    "character_count": 2,
    "role_type_dist": {
      "红生": 1,
      "净": 1
    },
    "narrative_curve": [
      0.0,
      0.0,
      0.875,
      0.882
    ],
    "musical_arc": [
      "二黄",
      null,
      "二黄",
      "西皮"
    ],
    "cooccurrence": {
      "赵匡胤|马童": 1,
      "赵匡胤|黄兴": 1,
      "马童|黄兴": 1,
      "呼延赞|赵匡胤": 2
    }
  },
  "scenes": [
    {
      "scene_index": 1,
      "label": "第一场",
      "characters_present": [
        "赵匡胤",
        "马童",
        "黄兴"
      ],
      "lines": [
        {
          "character": null,
          "line_type": "stage_direction",
          "musical_style": null,
          "style_family": null,
          "text": "（八龙套引赵匡胤同上，四太监同上。）"
        },
        {
          "character": "赵匡胤",
          "line_type": "引子",
          "musical_style": null,
          "style_family": null,
          "text": "龙争虎斗，这干戈，何日里罢休？"
        },
        {
          "character": "赵匡胤",
          "line_type": "念",
          "musical_style": null,
          "style_family": null,
          "text": "蛟龙无水困沙滩，似却明珠土内埋。奸贼诓孤河东地，不知何日转回还。"
        },
        {
          "character": "赵匡胤",
          "line_type": "白",
          "musical_style": null,
          "style_family": null,
          "text": "孤，乾德王赵。可恨欧阳藩将孤诓至河东，七载有余。困得孤内无粮草，外无"
        },
        {
          "character": "赵匡胤",
          "line_type": "白",
          "musical_style": null,
          "style_family": null,
          "text": "救兵。命黄兴前去打探，未见回报。"
        },
        {
          "character": null,
          "line_type": "stage_direction",
          "musical_style": null,
          "style_family": null,
          "text": "（黄兴上。）"
        },
        {
          "character": "黄兴",
          "line_type": "念",
          "musical_style": null,
          "style_family": null,
          "text": "打探军情事，奏与万岁知。"
        },
        {
          "character": "黄兴",
          "line_type": "白",
          "musical_style": null,
          "style_family": null,
          "text": "臣黄兴见驾，吾王万岁！"
        },
        {
          "character": "赵匡胤",
          "line_type": "白",
          "musical_style": null,
          "style_family": null,
          "text": "打探哪路军情，一一奏来。"
        },
        {
          "character": "黄兴",
          "line_type": "白",
          "musical_style": null,
          "style_family": null,
          "text": "臣探得罗家山发来一哨人马，昨日鞭坠白龙，今日叫骂御营，特来奏与万岁得"
        },
        {
          "character": "黄兴",
          "line_type": "白",
          "musical_style": null,
          "style_family": null,
          "text": "知。"
        },
        {
          "character": "赵匡胤",
          "line_type": "白",
          "musical_style": null,
          "style_family": null,
          "text": "再探！"
        },
        {
          "character": "黄兴",
          "line_type": "白",
          "musical_style": null,
          "style_family": null,
          "text": "领旨。"
        },
        {
          "character": null,
          "line_type": "stage_direction",
          "musical_style": null,
          "style_family": null,
          "text": "（黄兴下。）"
        },
        {
          "character": "赵匡胤",
          "line_type": "白",
          "musical_style": null,
          "style_family": null,
          "text": "且住，黄兴奏道：罗家山发来一哨人马，昨日鞭坠白龙，今日叫骂御营。此誓"
        },
        {
          "character": "赵匡胤",
          "line_type": "白",
          "musical_style": null,
          "style_family": null,
          "text": "叫孤难解也！"
        },
        {
          "character": null,
          "line_type": "stage_direction",
          "musical_style": null,
          "style_family": null,
          "text": "（唢呐二黄慢板）探马儿不住得飞来报："
        },
        {
          "character": null,
          "line_type": "stage_direction",
          "musical_style": null,
          "style_family": null,
          "text": "他报道罗家山兵发一哨。"
        },
        {
          "character": null,
          "line_type": "stage_direction",
          "musical_style": null,
          "style_family": null,
          "text": "吓坏了满营中大小英豪。"
        },
        {
          "character": null,
          "line_type": "stage_direction",
          "musical_style": null,
          "style_family": null,
          "text": "他要夺孤王的锦绣龙朝。"
        },
        {
          "character": null,
          "line_type": "stage_direction",
          "musical_style": null,
          "style_family": null,
          "text": "呼寿廷倒作了马前先行。"
        },
        {
          "character": null,
          "line_type": "stage_direction",
          "musical_style": null,
          "style_family": null,
          "text": "但不知何日里才的回朝？"
        },
        {
          "character": null,
          "line_type": "stage_direction",
          "musical_style": null,
          "style_family": null,
          "text": "在身上脱下了滚龙袍。"
        },
        {
          "character": "赵匡胤",
          "line_type": "白",
          "musical_style": null,
          "style_family": null,
          "text": "孤的玲珑吓！"
        },
        {
          "character": null,
          "line_type": "stage_direction",
          "musical_style": null,
          "style_family": null,
          "text": "（唢呐二黄慢板）玲珑铠甲丝条绕，"
        },
        {
          "character": null,
          "line_type": "stage_direction",
          "musical_style": null,
          "style_family": null,
          "text": "杀人妙计有千条。"
        },
        {
          "character": null,
          "line_type": "stage_direction",
          "musical_style": null,
          "style_family": null,
          "text": "（八龙套同下。）"
        },
        {
          "character": null,
          "line_type": "stage_direction",
          "musical_style": null,
          "style_family": null,
          "text": "赵匡胤 （唢呐二黄慢板）把守御营要勤劳。"
        },
        {
          "character": null,
          "line_type": "stage_direction",
          "musical_style": null,
          "style_family": null,
          "text": "（赵匡胤下。马童上，备马。）"
        },
        {
          "character": "马童",
          "line_type": "白",
          "musical_style": null,
          "style_family": null,
          "text": "请爷上马。"
        },
        {
          "character": null,
          "line_type": "stage_direction",
          "musical_style": null,
          "style_family": null,
          "text": "（赵匡胤上。）"
        },
        {
          "character": null,
          "line_type": "stage_direction",
          "musical_style": null,
          "style_family": null,
          "text": "赵匡胤 （唢呐二黄慢板）这是孤无能将亲把兵交。"
        },
        {
          "character": null,
          "line_type": "stage_direction",
          "musical_style": null,
          "style_family": null,
          "text": "（赵匡胤、马童同下。）"
        }
      ],
      "interactions": [
        {
          "edge": "黄兴→赵匡胤",
          "turns": 3
        },
        {
          "edge": "赵匡胤→黄兴",
          "turns": 2
        },
        {
          "edge": "赵匡胤→马童",
          "turns": 1
        }
      ],
      "stats": {
        "line_counts": {
          "stage_direction": 13,
          "念": 1,
          "白": 6
        },
        "singing_ratio": 0.0,
        "dominant_style_family": "二黄",
        "musical_styles": [
          "二黄慢板"
        ]
      },
      "scene_feature": [
        0.0,
        0.0667,
        0.8,
        0.1333,
        0.5,
        3,
        0.0,
        0.0
      ]
    },
    {
      "scene_index": 2,
      "label": "第二场",
      "characters_present": [
        "呼延赞"
      ],
      "lines": [
        {
          "character": null,
          "line_type": "stage_direction",
          "musical_style": null,
          "style_family": null,
          "text": "（〖急急风〗。呼延赞、八龙套同上。）"
        },
        {
          "character": "呼延赞",
          "line_type": "笑",
          "musical_style": null,
          "style_family": null,
          "text": "哈哈哈，吓，哈哈哈！"
        },
        {
          "character": null,
          "line_type": "stage_direction",
          "musical_style": null,
          "style_family": null,
          "text": "（呼延赞、八龙套同下。）"
        }
      ],
      "interactions": [],
      "stats": {
        "line_counts": {
          "stage_direction": 2
        },
        "singing_ratio": 0.0,
        "dominant_style_family": null,
        "musical_styles": []
      },
      "scene_feature": [
        0.0,
        0.0,
        1.0,
        0.0,
        0.0,
        1,
        0.0,
        0.0
      ]
    },
    {
      "scene_index": 3,
      "label": "第三场",
      "characters_present": [
        "一个斩字未曾出口",
        "三更时那胡儿前来偷营",
        "不通名姓走了罢",
        "催马儿来至在御营口",
        "呼延赞",
        "恨河东刘冲贼战表打定",
        "欧阳藩在金殿挂了帅印",
        "若问小将名和姓",
        "赵匡胤",
        "跨下了一骑乌骓马",
        "问一声小将名和姓"
      ],
      "lines": [
        {
          "character": null,
          "line_type": "stage_direction",
          "musical_style": null,
          "style_family": null,
          "text": "（赵匡胤上。）"
        },
        {
          "character": null,
          "line_type": "stage_direction",
          "musical_style": null,
          "style_family": null,
          "text": "赵匡胤 （唢呐二黄慢板）这是孤无能将亲把兵交。"
        },
        {
          "character": null,
          "line_type": "stage_direction",
          "musical_style": null,
          "style_family": null,
          "text": "（赵匡胤、马童同下。）"
        },
        {
          "character": null,
          "line_type": "stage_direction",
          "musical_style": null,
          "style_family": null,
          "text": "（〖急急风〗。呼延赞、八龙套同上。）"
        },
        {
          "character": "呼延赞",
          "line_type": "笑",
          "musical_style": null,
          "style_family": null,
          "text": "哈哈哈，吓，哈哈哈！"
        },
        {
          "character": null,
          "line_type": "stage_direction",
          "musical_style": null,
          "style_family": null,
          "text": "（呼延赞、八龙套同下。）"
        },
        {
          "character": null,
          "line_type": "stage_direction",
          "musical_style": null,
          "style_family": null,
          "text": "（赵匡胤上。）"
        },
        {
          "character": "赵匡胤",
          "line_type": "二黄摇板",
          "musical_style": "二黄摇板",
          "style_family": "二黄",
          "text": "催马来在战场道，"
        },
        {
          "character": "赵匡胤",
          "line_type": "二黄摇板",
          "musical_style": "二黄摇板",
          "style_family": "二黄",
          "text": "会一会罗家山那家英豪。"
        },
        {
          "character": null,
          "line_type": "stage_direction",
          "musical_style": null,
          "style_family": null,
          "text": "呼延赞 （内二黄导板） 乌骓马不住得吮声吼，"
        },
        {
          "character": null,
          "line_type": "stage_direction",
          "musical_style": null,
          "style_family": null,
          "text": "（呼延赞上。）"
        },
        {
          "character": "呼延赞",
          "line_type": "二黄慢板",
          "musical_style": "二黄慢板",
          "style_family": "二黄",
          "text": "打将鞭一举鬼神愁！"
        },
        {
          "character": "呼延赞",
          "line_type": "白",
          "musical_style": null,
          "style_family": null,
          "text": "呀呔！"
        },
        {
          "character": "呼延赞",
          "line_type": "二黄慢板",
          "musical_style": "二黄慢板",
          "style_family": "二黄",
          "text": "叫一声乾德王快出营头！"
        },
        {
          "character": "呼延赞",
          "line_type": "二黄慢板",
          "musical_style": "二黄慢板",
          "style_family": "二黄",
          "text": "催马儿来至在御营口"
        },
        {
          "character": "赵匡胤",
          "line_type": "二黄慢板",
          "musical_style": "二黄慢板",
          "style_family": "二黄",
          "text": "只见他乌油盔乌油甲，"
        },
        {
          "character": "赵匡胤",
          "line_type": "二黄慢板",
          "musical_style": "二黄慢板",
          "style_family": "二黄",
          "text": "皂罗袍上绣团花。"
        },
        {
          "character": "赵匡胤",
          "line_type": "二黄慢板",
          "musical_style": "二黄慢板",
          "style_family": "二黄",
          "text": "打将钢鞭手内拿。"
        },
        {
          "character": "赵匡胤",
          "line_type": "二黄慢板",
          "musical_style": "二黄慢板",
          "style_family": "二黄",
          "text": "通上名来好动杀法！"
        },
        {
          "character": "赵匡胤",
          "line_type": "二黄慢板",
          "musical_style": "二黄慢板",
          "style_family": "二黄",
          "text": "跨下了一骑乌骓马"
        },
        {
          "character": "赵匡胤",
          "line_type": "二黄慢板",
          "musical_style": "二黄慢板",
          "style_family": "二黄",
          "text": "问一声小将名和姓"
        },
        {
          "character": "呼延赞",
          "line_type": "二黄慢板",
          "musical_style": "二黄慢板",
          "style_family": "二黄",
          "text": "家住在河南汴梁城，"
        },
        {
          "character": "呼延赞",
          "line_type": "二黄慢板",
          "musical_style": "二黄慢板",
          "style_family": "二黄",
          "text": "我的父名叫呼寿廷。"
        },
        {
          "character": "呼延赞",
          "line_type": "二黄慢板",
          "musical_style": "二黄慢板",
          "style_family": "二黄",
          "text": "跨下了一骑乌骓马"
        },
        {
          "character": "呼延赞",
          "line_type": "二黄慢板",
          "musical_style": "二黄慢板",
          "style_family": "二黄",
          "text": "问一声小将名和姓"
        },
        {
          "character": "呼延赞",
          "line_type": "二黄摇板",
          "musical_style": "二黄摇板",
          "style_family": "二黄",
          "text": "就是少爷的名！"
        },
        {
          "character": "呼延赞",
          "line_type": "二黄摇板",
          "musical_style": "二黄摇板",
          "style_family": "二黄",
          "text": "若问小将名和姓"
        },
        {
          "character": "呼延赞",
          "line_type": "二黄摇板",
          "musical_style": "二黄摇板",
          "style_family": "二黄",
          "text": "呼延赞"
        },
        {
          "character": "赵匡胤",
          "line_type": "二黄摇板",
          "musical_style": "二黄摇板",
          "style_family": "二黄",
          "text": "孤道呼家无有后，"
        },
        {
          "character": "赵匡胤",
          "line_type": "二黄摇板",
          "musical_style": "二黄摇板",
          "style_family": "二黄",
          "text": "原来还有后代根。"
        },
        {
          "character": "赵匡胤",
          "line_type": "二黄摇板",
          "musical_style": "二黄摇板",
          "style_family": "二黄",
          "text": "不通名姓走了罢"
        },
        {
          "character": "呼延赞",
          "line_type": "二黄摇板",
          "musical_style": "二黄摇板",
          "style_family": "二黄",
          "text": "钢鞭不打无名人！"
        },
        {
          "character": "赵匡胤",
          "line_type": "二黄摇板",
          "musical_style": "二黄摇板",
          "style_family": "二黄",
          "text": "乾德王现在黄罗帐，"
        },
        {
          "character": "赵匡胤",
          "line_type": "二黄摇板",
          "musical_style": "二黄摇板",
          "style_family": "二黄",
          "text": "我是他驾前一小军。"
        },
        {
          "character": "呼延赞",
          "line_type": "二黄摇板",
          "musical_style": "二黄摇板",
          "style_family": "二黄",
          "text": "看你不像军家样，"
        },
        {
          "character": "呼延赞",
          "line_type": "二黄摇板",
          "musical_style": "二黄摇板",
          "style_family": "二黄",
          "text": "定是御营乾德王！"
        },
        {
          "character": "赵匡胤",
          "line_type": "二黄摇板",
          "musical_style": "二黄摇板",
          "style_family": "二黄",
          "text": "少有关西闯帝邦，"
        },
        {
          "character": "赵匡胤",
          "line_type": "二黄摇板",
          "musical_style": "二黄摇板",
          "style_family": "二黄",
          "text": "岂肯过伏小儿郎？"
        },
        {
          "character": "赵匡胤",
          "line_type": "二黄摇板",
          "musical_style": "二黄摇板",
          "style_family": "二黄",
          "text": "孤就是御营乾德王！"
        },
        {
          "character": null,
          "line_type": "stage_direction",
          "musical_style": null,
          "style_family": null,
          "text": "（赵匡胤、呼延赞同开打，赵匡胤下，呼延赞追下。赵匡胤上。）"
        },
        {
          "character": "赵匡胤",
          "line_type": "二黄摇板",
          "musical_style": "二黄摇板",
          "style_family": "二黄",
          "text": "催马来在战场下，"
        },
        {
          "character": "赵匡胤",
          "line_type": "二黄摇板",
          "musical_style": "二黄摇板",
          "style_family": "二黄",
          "text": "小将到来顺说他。"
        },
        {
          "character": null,
          "line_type": "stage_direction",
          "musical_style": null,
          "style_family": null,
          "text": "（呼延赞上。）"
        },
        {
          "character": "呼延赞",
          "line_type": "二黄摇板",
          "musical_style": "二黄摇板",
          "style_family": "二黄",
          "text": "我父身犯何条律，"
        },
        {
          "character": "呼延赞",
          "line_type": "二黄摇板",
          "musical_style": "二黄摇板",
          "style_family": "二黄",
          "text": "为何一命问斩刑？"
        },
        {
          "character": "赵匡胤",
          "line_type": "二黄导板",
          "musical_style": "二黄导板",
          "style_family": "二黄",
          "text": "小将军暂息雷霆怒，"
        },
        {
          "character": "赵匡胤",
          "line_type": "二黄慢板",
          "musical_style": "二黄慢板",
          "style_family": "二黄",
          "text": "细听孤王说分明："
        },
        {
          "character": "赵匡胤",
          "line_type": "二黄慢板",
          "musical_style": "二黄慢板",
          "style_family": "二黄",
          "text": "他要夺孤王的锦绣龙廷。"
        },
        {
          "character": "赵匡胤",
          "line_type": "二黄慢板",
          "musical_style": "二黄慢板",
          "style_family": "二黄",
          "text": "你的父倒作了马前先行。"
        },
        {
          "character": "赵匡胤",
          "line_type": "二黄慢板",
          "musical_style": "二黄慢板",
          "style_family": "二黄",
          "text": "满营中俱言道反了寿廷。"
        },
        {
          "character": "赵匡胤",
          "line_type": "二黄慢板",
          "musical_style": "二黄慢板",
          "style_family": "二黄",
          "text": "欧阳藩拔宝剑杀尔的父亲！"
        },
        {
          "character": "赵匡胤",
          "line_type": "二黄慢板",
          "musical_style": "二黄慢板",
          "style_family": "二黄",
          "text": "恨河东刘冲贼战表打定"
        },
        {
          "character": "赵匡胤",
          "line_type": "二黄慢板",
          "musical_style": "二黄慢板",
          "style_family": "二黄",
          "text": "欧阳藩在金殿挂了帅印"
        },
        {
          "character": "赵匡胤",
          "line_type": "二黄慢板",
          "musical_style": "二黄慢板",
          "style_family": "二黄",
          "text": "三更时那胡儿前来偷营"
        },
        {
          "character": "赵匡胤",
          "line_type": "二黄慢板",
          "musical_style": "二黄慢板",
          "style_family": "二黄",
          "text": "一个斩字未曾出口"
        },
        {
          "character": "呼延赞",
          "line_type": "二黄摇板",
          "musical_style": "二黄摇板",
          "style_family": "二黄",
          "text": "君不传旨谁敢斩？"
        },
        {
          "character": "呼延赞",
          "line_type": "二黄摇板",
          "musical_style": "二黄摇板",
          "style_family": "二黄",
          "text": "哪一个大胆乱杀人！"
        },
        {
          "character": "赵匡胤",
          "line_type": "二黄摇板",
          "musical_style": "二黄摇板",
          "style_family": "二黄",
          "text": "兵权落在奸贼手，"
        },
        {
          "character": "赵匡胤",
          "line_type": "二黄摇板",
          "musical_style": "二黄摇板",
          "style_family": "二黄",
          "text": "孤王也要听令行。"
        },
        {
          "character": "呼延赞",
          "line_type": "二黄摇板",
          "musical_style": "二黄摇板",
          "style_family": "二黄",
          "text": "不会为君死了罢，"
        },
        {
          "character": "呼延赞",
          "line_type": "二黄摇板",
          "musical_style": "二黄摇板",
          "style_family": "二黄",
          "text": "苍天再降紫微星！"
        },
        {
          "character": "赵匡胤",
          "line_type": "二黄摇板",
          "musical_style": "二黄摇板",
          "style_family": "二黄",
          "text": "小将保孤回朝转，"
        },
        {
          "character": "赵匡胤",
          "line_type": "二黄摇板",
          "musical_style": "二黄摇板",
          "style_family": "二黄",
          "text": "孤封你前殿王？"
        },
        {
          "character": "呼延赞",
          "line_type": "白",
          "musical_style": null,
          "style_family": null,
          "text": "不要！"
        },
        {
          "character": "赵匡胤",
          "line_type": "二黄摇板",
          "musical_style": "二黄摇板",
          "style_family": "二黄",
          "text": "后殿王？"
        },
        {
          "character": "呼延赞",
          "line_type": "白",
          "musical_style": null,
          "style_family": null,
          "text": "不要！"
        },
        {
          "character": "赵匡胤",
          "line_type": "二黄摇板",
          "musical_style": "二黄摇板",
          "style_family": "二黄",
          "text": "一十八驾总兵王？"
        },
        {
          "character": "呼延赞",
          "line_type": "白",
          "musical_style": null,
          "style_family": null,
          "text": "呸！"
        },
        {
          "character": "呼延赞",
          "line_type": "二黄摇板",
          "musical_style": "二黄摇板",
          "style_family": "二黄",
          "text": "万里江山我不要，"
        },
        {
          "character": "呼延赞",
          "line_type": "二黄摇板",
          "musical_style": "二黄摇板",
          "style_family": "二黄",
          "text": "一心要报杀父仇！"
        },
        {
          "character": "赵匡胤",
          "line_type": "二黄摇板",
          "musical_style": "二黄摇板",
          "style_family": "二黄",
          "text": "小将不必逞刚强，"
        },
        {
          "character": "呼延赞",
          "line_type": "二黄摇板",
          "musical_style": "二黄摇板",
          "style_family": "二黄",
          "text": "罗家山前自为王！"
        },
        {
          "character": "赵匡胤",
          "line_type": "二黄摇板",
          "musical_style": "二黄摇板",
          "style_family": "二黄",
          "text": "孤王与你分上下！"
        },
        {
          "character": null,
          "line_type": "stage_direction",
          "musical_style": null,
          "style_family": null,
          "text": "（赵匡胤、呼延赞同开打，赵匡胤下，呼延赞追下。）"
        }
      ],
      "interactions": [
        {
          "edge": "赵匡胤→呼延赞",
          "turns": 11
        },
        {
          "edge": "呼延赞→赵匡胤",
          "turns": 11
        }
      ],
      "stats": {
        "line_counts": {
          "stage_direction": 10,
          "唱": 21,
          "白": 3
        },
        "singing_ratio": 0.875,
        "dominant_style_family": "二黄",
        "musical_styles": [
          "二黄导板",
          "二黄慢板",
          "二黄摇板"
        ]
      },
      "scene_feature": [
        0.875,
        0.9206,
        0.0794,
        0.0,
        0.371,
        2,
        0.0,
        0.9206
      ]
    },
    {
      "scene_index": 4,
      "label": "第四场",
      "characters_present": [
        "呼延赞",
        "呼延赞保主若有假",
        "在马上擒孤擒不住",
        "左思右想不下马",
        "手使金锏朝下打",
        "手使钢鞭朝下打",
        "扳鞍离镫下战马",
        "猛然间睁开了丹凤眼",
        "赵匡胤"
      ],
      "lines": [
        {
          "character": null,
          "line_type": "stage_direction",
          "musical_style": null,
          "style_family": null,
          "text": "（龙形、虎形同上。赵匡胤上，呼延赞追上。）"
        },
        {
          "character": "赵匡胤",
          "line_type": "二黄导板",
          "musical_style": "二黄导板",
          "style_family": "二黄",
          "text": "人困马乏难交战，"
        },
        {
          "character": "赵匡胤",
          "line_type": "白",
          "musical_style": null,
          "style_family": null,
          "text": "吓！"
        },
        {
          "character": "赵匡胤",
          "line_type": "二黄摇板",
          "musical_style": "二黄摇板",
          "style_family": "二黄",
          "text": "只见小将睡雕鞍。"
        },
        {
          "character": "赵匡胤",
          "line_type": "二黄摇板",
          "musical_style": "二黄摇板",
          "style_family": "二黄",
          "text": "只见黑虎奔了山！"
        },
        {
          "character": "赵匡胤",
          "line_type": "二黄摇板",
          "musical_style": "二黄摇板",
          "style_family": "二黄",
          "text": "手使金锏朝下打"
        },
        {
          "character": "呼延赞",
          "line_type": "二黄导板",
          "musical_style": "二黄导板",
          "style_family": "二黄",
          "text": "梦儿里梦见了我父到，"
        },
        {
          "character": "呼延赞",
          "line_type": "二黄导板",
          "musical_style": "二黄导板",
          "style_family": "二黄",
          "text": "手使金锏朝下打"
        },
        {
          "character": "呼延赞",
          "line_type": "白",
          "musical_style": null,
          "style_family": null,
          "text": "吓！"
        },
        {
          "character": "呼延赞",
          "line_type": "白",
          "musical_style": null,
          "style_family": null,
          "text": "手使金锏朝下打"
        },
        {
          "character": "呼延赞",
          "line_type": "二黄摇板",
          "musical_style": "二黄摇板",
          "style_family": "二黄",
          "text": "只见昏王睡鞍鞒。"
        },
        {
          "character": "呼延赞",
          "line_type": "二黄摇板",
          "musical_style": "二黄摇板",
          "style_family": "二黄",
          "text": "只见赤火龙一条！"
        },
        {
          "character": "呼延赞",
          "line_type": "二黄摇板",
          "musical_style": "二黄摇板",
          "style_family": "二黄",
          "text": "三呼万岁饶恕咱！"
        },
        {
          "character": "呼延赞",
          "line_type": "二黄摇板",
          "musical_style": "二黄摇板",
          "style_family": "二黄",
          "text": "手使钢鞭朝下打"
        },
        {
          "character": "呼延赞",
          "line_type": "二黄摇板",
          "musical_style": "二黄摇板",
          "style_family": "二黄",
          "text": "扳鞍离镫下战马"
        },
        {
          "character": "赵匡胤",
          "line_type": "西皮导板",
          "musical_style": "西皮导板",
          "style_family": "西皮",
          "text": "耳边厢又听得三呼万岁，"
        },
        {
          "character": "赵匡胤",
          "line_type": "西皮导板",
          "musical_style": "西皮导板",
          "style_family": "西皮",
          "text": "手使钢鞭朝下打"
        },
        {
          "character": "赵匡胤",
          "line_type": "西皮导板",
          "musical_style": "西皮导板",
          "style_family": "西皮",
          "text": "扳鞍离镫下战马"
        },
        {
          "character": "赵匡胤",
          "line_type": "西皮慢板",
          "musical_style": "西皮慢板",
          "style_family": "西皮",
          "text": "想必是我朝中发来救兵。"
        },
        {
          "character": "赵匡胤",
          "line_type": "西皮慢板",
          "musical_style": "西皮慢板",
          "style_family": "西皮",
          "text": "猛然间睁开了丹凤眼"
        },
        {
          "character": "呼延赞",
          "line_type": "白",
          "musical_style": null,
          "style_family": null,
          "text": "万岁！"
        },
        {
          "character": "赵匡胤",
          "line_type": "西皮慢板",
          "musical_style": "西皮慢板",
          "style_family": "西皮",
          "text": "又只见，"
        },
        {
          "character": "赵匡胤",
          "line_type": "西皮快板",
          "musical_style": "西皮快板",
          "style_family": "西皮",
          "text": "小将跌跪在马前。"
        },
        {
          "character": "赵匡胤",
          "line_type": "西皮快板",
          "musical_style": "西皮快板",
          "style_family": "西皮",
          "text": "诓孤下马难上难！"
        },
        {
          "character": "赵匡胤",
          "line_type": "西皮快板",
          "musical_style": "西皮快板",
          "style_family": "西皮",
          "text": "在马上擒孤擒不住"
        },
        {
          "character": "呼延赞",
          "line_type": "西皮快板",
          "musical_style": "西皮快板",
          "style_family": "西皮",
          "text": "万岁不必心害怕，"
        },
        {
          "character": "呼延赞",
          "line_type": "西皮快板",
          "musical_style": "西皮快板",
          "style_family": "西皮",
          "text": "呼延赞保你坐中华！"
        },
        {
          "character": "赵匡胤",
          "line_type": "西皮快板",
          "musical_style": "西皮快板",
          "style_family": "西皮",
          "text": "你若保孤坐中华，"
        },
        {
          "character": "赵匡胤",
          "line_type": "西皮快板",
          "musical_style": "西皮快板",
          "style_family": "西皮",
          "text": "可对苍天把誓发？"
        },
        {
          "character": "呼延赞",
          "line_type": "西皮快板",
          "musical_style": "西皮快板",
          "style_family": "西皮",
          "text": "万岁命我把誓发，"
        },
        {
          "character": "呼延赞",
          "line_type": "西皮快板",
          "musical_style": "西皮快板",
          "style_family": "西皮",
          "text": "尊一声苍天听根芽："
        },
        {
          "character": "呼延赞",
          "line_type": "西皮快板",
          "musical_style": "西皮快板",
          "style_family": "西皮",
          "text": "死在千军万马踏！"
        },
        {
          "character": "呼延赞",
          "line_type": "西皮快板",
          "musical_style": "西皮快板",
          "style_family": "西皮",
          "text": "呼延赞保主若有假"
        },
        {
          "character": "赵匡胤",
          "line_type": "西皮快板",
          "musical_style": "西皮快板",
          "style_family": "西皮",
          "text": "一见小将把誓发，"
        },
        {
          "character": "赵匡胤",
          "line_type": "西皮快板",
          "musical_style": "西皮快板",
          "style_family": "西皮",
          "text": "不由孤王喜笑发。"
        },
        {
          "character": "赵匡胤",
          "line_type": "西皮快板",
          "musical_style": "西皮快板",
          "style_family": "西皮",
          "text": "金锏挑起小卿家。"
        },
        {
          "character": "赵匡胤",
          "line_type": "西皮快板",
          "musical_style": "西皮快板",
          "style_family": "西皮",
          "text": "左思右想不下马"
        },
        {
          "character": "呼延赞",
          "line_type": "西皮快板",
          "musical_style": "西皮快板",
          "style_family": "西皮",
          "text": "走上前来参王驾，"
        },
        {
          "character": "赵匡胤",
          "line_type": "西皮快板",
          "musical_style": "西皮快板",
          "style_family": "西皮",
          "text": "孤王传旨且平身。"
        },
        {
          "character": "呼延赞",
          "line_type": "西皮快板",
          "musical_style": "西皮快板",
          "style_family": "西皮",
          "text": "杀父仇人哪一个？"
        },
        {
          "character": "赵匡胤",
          "line_type": "西皮快板",
          "musical_style": "西皮快板",
          "style_family": "西皮",
          "text": "欧阳藩是尔对头人！"
        },
        {
          "character": "呼延赞",
          "line_type": "西皮快板",
          "musical_style": "西皮快板",
          "style_family": "西皮",
          "text": "问声奸贼今何在？"
        },
        {
          "character": "赵匡胤",
          "line_type": "白",
          "musical_style": null,
          "style_family": null,
          "text": "随孤来，"
        },
        {
          "character": "赵匡胤",
          "line_type": "西皮快板",
          "musical_style": "西皮快板",
          "style_family": "西皮",
          "text": "不在前营在后营。"
        },
        {
          "character": "呼延赞",
          "line_type": "西皮快板",
          "musical_style": "西皮快板",
          "style_family": "西皮",
          "text": "辞王别驾跨战马，"
        },
        {
          "character": "呼延赞",
          "line_type": "西皮快板",
          "musical_style": "西皮快板",
          "style_family": "西皮",
          "text": "后营去把奸贼杀！"
        },
        {
          "character": null,
          "line_type": "stage_direction",
          "musical_style": null,
          "style_family": null,
          "text": "（三笑） 哈哈哈，吓，哈哈哈！"
        },
        {
          "character": "赵匡胤",
          "line_type": "西皮快板",
          "musical_style": "西皮快板",
          "style_family": "西皮",
          "text": "喜呵呵来笑呵呵，"
        },
        {
          "character": "赵匡胤",
          "line_type": "西皮快板",
          "musical_style": "西皮快板",
          "style_family": "西皮",
          "text": "孤王收了黑阎罗。"
        },
        {
          "character": "赵匡胤",
          "line_type": "西皮快板",
          "musical_style": "西皮快板",
          "style_family": "西皮",
          "text": "哪怕胡儿动干戈！"
        },
        {
          "character": null,
          "line_type": "stage_direction",
          "musical_style": null,
          "style_family": null,
          "text": "（赵匡胤、呼延赞同下。）"
        }
      ],
      "interactions": [
        {
          "edge": "赵匡胤→呼延赞",
          "turns": 8
        },
        {
          "edge": "呼延赞→赵匡胤",
          "turns": 8
        }
      ],
      "stats": {
        "line_counts": {
          "stage_direction": 11,
          "唱": 15,
          "白": 2
        },
        "singing_ratio": 0.882,
        "dominant_style_family": "西皮",
        "musical_styles": [
          "二黄导板",
          "二黄摇板",
          "西皮导板",
          "西皮快板",
          "西皮慢板"
        ]
      },
      "scene_feature": [
        0.882,
        0.8958,
        0.1042,
        0.0,
        0.3404,
        2,
        0.6667,
        0.2292
      ]
    }
  ]
}